[
{"Initial_Urls": "https://digitalterminal.in/tech-stories"},
{"Initial_Urls": "https://digitalterminal.in/dt-buyers-guide"},
{"Initial_Urls": "https://digitalterminal.in/partner-summit"},
{"Initial_Urls": "https://digitalterminal.in/tech-companies"},
{"Initial_Urls": "https://digitalterminal.in/government"},
{"Initial_Urls": "https://digitalterminal.in/webinar"},
{"Initial_Urls": "https://digitalterminal.in/health-tech"},
{"Initial_Urls": "https://digitalterminal.in/tech"},
{"Initial_Urls": "https://digitalterminal.in/edutech"},
{"Initial_Urls": "https://digitalterminal.in/dt-edition"},
{"Initial_Urls": "https://digitalterminal.in/dt-events"},
{"Initial_Urls": "https://digitalterminal.in/solutions"},
{"Initial_Urls": "https://digitalterminal.in/dtv"},
{"Initial_Urls": "https://digitalterminal.in/gaming"},
{"Initial_Urls": "https://digitalterminal.in/infotainment"},
{"Initial_Urls": "https://digitalterminal.in/startup"},
{"Initial_Urls": "https://digitalterminal.in/smart-phone"},
{"Initial_Urls": "https://digitalterminal.in/launchpad"},
{"Initial_Urls": "https://digitalterminal.in/opinion"},
{"Initial_Urls": "https://digitalterminal.in/resource"},
{"Initial_Urls": "https://digitalterminal.in/case-study"},
{"Initial_Urls": "https://www.indiatvnews.com/delhi"},
{"Initial_Urls": "https://www.indiatvnews.com/mizoram"},
{"Initial_Urls": "https://www.indiatvnews.com/tamil-nadu"},
{"Initial_Urls": "https://www.indiatvnews.com/jammu-and-kashmir"},
{"Initial_Urls": "https://www.indiatvnews.com/livetv"},
{"Initial_Urls": "https://www.indiatvnews.com/uttar-pradesh"},
{"Initial_Urls": "https://www.indiatvnews.com/bihar"},
{"Initial_Urls": "https://www.jagran.com/advertise-withus.html"},
{"Initial_Urls": "https://www.jagran.com/citizen-journalism-hindi.html"},
{"Initial_Urls": "https://www.indiatvnews.com/sports/football"},
{"Initial_Urls": "https://www.indiatvnews.com/rajasthan"},
{"Initial_Urls": "https://www.indiatvnews.com/business/budget"},
{"Initial_Urls": "https://www.indiatvnews.com/karnataka"},
{"Initial_Urls": "https://www.jagran.com/news/education-news-hindi.html"},
{"Initial_Urls": "https://www.jagran.com/news/job-news-hindi.html"},
{"Initial_Urls": "https://www.jagran.com/news/career-news-hindi.html"},
{"Initial_Urls": "https://www.indiatvnews.com/weather-forecast"},
{"Initial_Urls": "https://www.jagran.com/sitemap.html"},
{"Initial_Urls": "https://www.indiatvnews.com/health"},
{"Initial_Urls": "https://www.jagran.com/about-us.html"},
{"Initial_Urls": "https://www.indiatvnews.com/india/national"},
{"Initial_Urls": "https://www.indiatvnews.com/education/career"},
{"Initial_Urls": "https://www.jagran.com/lifestyle/miscellaneous-news-hindi.html"},
{"Initial_Urls": "https://www.jagran.com/cricket/bouncer-news-hindi.html"},
{"Initial_Urls": "https://www.jagran.com/lifestyle/fashion-beauty-news-hindi.html"},
{"Initial_Urls": "https://www.jagran.com/lifestyle/health-news-hindi.html"},
{"Initial_Urls": "https://www.jagran.com/lifestyle/travel-tourism-news-hindi.html"},
{"Initial_Urls": "https://www.indiatvnews.com/entertainment/ott"},
{"Initial_Urls": "https://www.jagran.com/business/expert-column-news-hindi.html"},
{"Initial_Urls": "https://www.jagran.com/business/insurance-news-hindi.html"},
{"Initial_Urls": "https://www.jagran.com/business/savings-news-hindi.html"},
{"Initial_Urls": "https://www.jagran.com/business/investment-tax-news-hindi.html"},
{"Initial_Urls": "https://www.jagran.com/business/banking-loan-news-hindi.html"},
{"Initial_Urls": "https://www.jagran.com/lifestyle-hindi.html"},
{"Initial_Urls": "https://www.jagran.com/spiritual/mukhye-dharmik-sthal-news-hindi.html"},
{"Initial_Urls": "https://www.jagran.com/spiritual/sant-saadhak-news-hindi.html"},
{"Initial_Urls": "https://www.jagran.com/spiritual/puja-path-news-hindi.html"},
{"Initial_Urls": "https://www.jagran.com/spiritual/yog-news-hindi.html"},
{"Initial_Urls": "https://www.jagran.com/spiritual/auspicious-days-news-hindi.html"},
{"Initial_Urls": "https://www.jagran.com/spiritual/religion-news-hindi.html"},
{"Initial_Urls": "https://www.jagran.com/spiritual/panchang-news-hindi.html"},
{"Initial_Urls": "https://www.jagran.com/cricket/headlines-news-hindi.html"},
{"Initial_Urls": "https://www.jagran.com/entertainment/reviews-news-hindi.html"},
{"Initial_Urls": "https://www.jagran.com/spiritual-hindi.html"},
{"Initial_Urls": "https://www.jagran.com/entertainment/tv-news-hindi.html"},
{"Initial_Urls": "https://www.jagran.com/entertainment/bollywood-news-hindi.html"},
{"Initial_Urls": "https://www.jagran.com/entertainment/box-office-news-hindi.html"},
{"Initial_Urls": "https://www.jagran.com/cricket/experts-news-hindi.html"},
{"Initial_Urls": "https://www.jagran.com/cricket/apni-baat-news-hindi.html"},
{"Initial_Urls": "https://www.jagran.com/photogallery/technology-hindi.html"},
{"Initial_Urls": "https://www.jagran.com/photogallery/religion-hindi.html"},
{"Initial_Urls": "https://www.jagran.com/photogallery/cricket-hindi.html"},
{"Initial_Urls": "https://www.jagran.com/gujarat/vadodara"},
{"Initial_Urls": "https://www.jagran.com/gujarat/surat"},
{"Initial_Urls": "https://www.jagran.com/gujarat/ahmedabad"},
{"Initial_Urls": "https://www.jagran.com/madhya-pradesh/bhopal"},
{"Initial_Urls": "https://www.jagran.com/rajasthan/jaipur"},
{"Initial_Urls": "https://www.jagran.com/chhattisgarh/bilaspur-chhattisgarh"},
{"Initial_Urls": "https://www.jagran.com/chhattisgarh/raipur"},
{"Initial_Urls": "https://www.jagran.com/jammu-and-kashmir/poonch"},
{"Initial_Urls": "https://www.jagran.com/jammu-and-kashmir/srinagar"},
{"Initial_Urls": "https://www.jagran.com/himachal-pradesh/bilaspur-hp"},
{"Initial_Urls": "https://www.jagran.com/jammu-and-kashmir/jammu"},
{"Initial_Urls": "https://www.jagran.com/gujarat"},
{"Initial_Urls": "https://www.jagran.com/himachal-pradesh/mandi"},
{"Initial_Urls": "https://www.jagran.com/rajasthan"},
{"Initial_Urls": "https://www.jagran.com/himachal-pradesh/shimla"},
{"Initial_Urls": "https://www.jagran.com/odisha/puri"},
{"Initial_Urls": "https://www.jagran.com/odisha/cuttack"},
{"Initial_Urls": "https://www.jagran.com/maharashtra"},
{"Initial_Urls": "https://www.jagran.com/west-bengal/jalpaiguri"},
{"Initial_Urls": "https://www.jagran.com/west-bengal/darjeeling"},
{"Initial_Urls": "https://www.jagran.com/west-bengal/kolkata"},
{"Initial_Urls": "https://www.jagran.com/odisha/bhubaneshwar"},
{"Initial_Urls": "https://www.jagran.com/jharkhand/dhanbad"},
{"Initial_Urls": "https://www.jagran.com/maharashtra/pune"},
{"Initial_Urls": "https://www.jagran.com/maharashtra/nagpur"},
{"Initial_Urls": "https://www.jagran.com/maharashtra/mumbai"},
{"Initial_Urls": "https://www.jagran.com/jharkhand/hazaribagh"},
{"Initial_Urls": "https://www.jagran.com/delhi/new-delhi-city"},
{"Initial_Urls": "https://www.jagran.com/jharkhand/giridih"},
{"Initial_Urls": "https://www.jagran.com/jharkhand/jamshedpur"},
{"Initial_Urls": "https://www.jagran.com/delhi-ncr"},
{"Initial_Urls": "https://www.jagran.com/jharkhand/ranchi"},
{"Initial_Urls": "https://www.jagran.com/haryana"},
{"Initial_Urls": "https://www.jagran.com/punjab/amritsar"},
{"Initial_Urls": "https://www.jagran.com/haryana/ambala"},
{"Initial_Urls": "https://www.jagran.com/haryana/panipat"},
{"Initial_Urls": "https://www.jagran.com/haryana/rohtak"},
{"Initial_Urls": "https://www.jagran.com/haryana/gurgaon"},
{"Initial_Urls": "https://www.jagran.com/haryana/panchkula"},
{"Initial_Urls": "https://www.jagran.com/uttarakhand/udhamsingh-nagar"},
{"Initial_Urls": "https://www.jagran.com/punjab/ropar"},
{"Initial_Urls": "https://www.jagran.com/jharkhand"},
{"Initial_Urls": "https://www.jagran.com/uttarakhand/dehradun-city"},
{"Initial_Urls": "https://www.jagran.com/punjab/ludhiana"},
{"Initial_Urls": "https://www.jagran.com/uttarakhand"},
{"Initial_Urls": "https://www.jagran.com/punjab/jalandhar-city"},
{"Initial_Urls": "https://www.jagran.com/uttarakhand/haridwar"},
{"Initial_Urls": "https://www.jagran.com/punjab/chandigarh"},
{"Initial_Urls": "https://www.jagran.com/uttarakhand/almora"},
{"Initial_Urls": "https://www.jagran.com/bihar"},
{"Initial_Urls": "https://www.jagran.com/uttar-pradesh/agra-city"},
{"Initial_Urls": "https://www.jagran.com/uttarakhand/nainital"},
{"Initial_Urls": "https://www.jagran.com/bihar/muzaffarpur"},
{"Initial_Urls": "https://www.jagran.com/uttar-pradesh/lucknow-city"},
{"Initial_Urls": "https://www.jagran.com/uttar-pradesh"},
{"Initial_Urls": "https://www.jagran.com/bihar/bhagalpur"},
{"Initial_Urls": "https://www.jagran.com/uttar-pradesh/meerut-city"},
{"Initial_Urls": "https://www.jagran.com/uttar-pradesh/kanpur-city"},
{"Initial_Urls": "https://www.jagran.com/news/oddnews-news-hindi.html"},
{"Initial_Urls": "https://www.jagran.com/sports-news-hindi.html"},
{"Initial_Urls": "https://www.jagran.com/editorial/apnibaat-news-hindi.html"},
{"Initial_Urls": "https://www.jagran.com/bihar/darbhanga"},
{"Initial_Urls": "https://www.jagran.com/automobile/car-buyer-guide-news-hindi.html"},
{"Initial_Urls": "https://www.jagran.com/bihar/gaya"},
{"Initial_Urls": "https://www.jagran.com/bihar/patna-city"},
{"Initial_Urls": "https://www.jagran.com/punjab"},
{"Initial_Urls": "https://www.jagran.com/business/biz-news-hindi.html"},
{"Initial_Urls": "https://www.jagran.com/uttar-pradesh/prayagraj"},
{"Initial_Urls": "https://www.jagran.com/editorial/nazariya-news-hindi.html"},
{"Initial_Urls": "https://www.jagran.com/editorial-hindi.html"},
{"Initial_Urls": "https://www.jagran.com/automobile/new-car-launches-news-hindi.html"},
{"Initial_Urls": "https://www.jagran.com/automobile/latest-news-news-hindi.html"},
{"Initial_Urls": "https://www.jagran.com/automobile/car-reviews-news-hindi.html"},
{"Initial_Urls": "https://www.jagran.com/technology/review-news-hindi.html"},
{"Initial_Urls": "https://www.jagran.com/technology/social-media-news-hindi.html"},
{"Initial_Urls": "https://www.jagran.com/technology/tech-guide-news-hindi.html"},
{"Initial_Urls": "https://www.jagran.com/technology/apps-news-hindi.html"},
{"Initial_Urls": "https://www.jagran.com/technology/latest-launch-news-hindi.html"},
{"Initial_Urls": "https://www.jagran.com/technology/tech-news-news-hindi.html"},
{"Initial_Urls": "https://www.jagran.com/cricket-hindi.html"},
{"Initial_Urls": "https://www.jagran.com/world-news-hindi.html"},
{"Initial_Urls": "https://www.livemint.com/elections/lok-sabha"},
{"Initial_Urls": "https://www.jagran.com/common-man-issue-news-hindi.html"},
{"Initial_Urls": "https://www.livemint.com/market/quarterly-results-calendar"},
{"Initial_Urls": "https://www.livemint.com/bank-holidays-india"},
{"Initial_Urls": "https://www.jagran.com/videos.html"},
{"Initial_Urls": "https://www.jagran.com/technology-hindi.html"},
{"Initial_Urls": "https://www.jagran.com/news/national-news-hindi.html"},
{"Initial_Urls": "https://www.jagran.com/entertainment-hindi.html"},
{"Initial_Urls": "https://www.jagran.com/"},
{"Initial_Urls": "https://www.jagran.com/business-hindi.html"},
{"Initial_Urls": "https://www.livemint.com/mostpopular"},
{"Initial_Urls": "https://www.livemint.com/latest-news"},
{"Initial_Urls": "https://www.jagran.com/feature-news-hindi.html"},
{"Initial_Urls": "https://www.livemint.com/web-stories"},
{"Initial_Urls": "https://www.livemint.com/premium"},
{"Initial_Urls": "https://www.livemint.com/market/market-stats/"},
{"Initial_Urls": "https://www.jagran.com/elections.html"},
{"Initial_Urls": "https://www.livemint.com/fuel-prices-diesel"},
{"Initial_Urls": "https://www.jagran.com/politics-news-hindi.html"},
{"Initial_Urls": "https://www.jagran.com/latest-news.html"},
{"Initial_Urls": "https://www.livemint.com/economy"},
{"Initial_Urls": "https://www.livemint.com/fuel-prices"},
{"Initial_Urls": "https://www.livemint.com/fuel-prices-petrol"},
{"Initial_Urls": "https://www.livemint.com/budget"},
{"Initial_Urls": "https://www.livemint.com/elections/assembly-elections"},
{"Initial_Urls": "https://www.livemint.com/elections"},
{"Initial_Urls": "https://www.livemint.com/ifsc-code"},
{"Initial_Urls": "https://www.livemint.com/budget/economic-survey"},
{"Initial_Urls": "https://www.livemint.com/budget/expectations"},
{"Initial_Urls": "https://www.livemint.com/elections/lok-sabha-elections"},
{"Initial_Urls": "https://www.livemint.com/market/live-blog"},
{"Initial_Urls": "https://www.livemint.com/market/ipo"},
{"Initial_Urls": "https://www.livemint.com/elections/assembly-election-2018"},
{"Initial_Urls": "https://www.livemint.com/market/commodities"},
{"Initial_Urls": "https://www.livemint.com/brand-post"},
{"Initial_Urls": "https://www.livemint.com/market"},
{"Initial_Urls": "https://www.livemint.com/market/cryptocurrency"},
{"Initial_Urls": "https://www.livemint.com/special-reports"},
{"Initial_Urls": "https://www.livemint.com/market/stock-market-news"},
{"Initial_Urls": "https://www.livemint.com/special-reports/native-content"},
{"Initial_Urls": "https://www.livemint.com/mutual-fund/mf-news"},
{"Initial_Urls": "https://www.livemint.com/insurance"},
{"Initial_Urls": "https://www.livemint.com/news"},
{"Initial_Urls": "https://www.livemint.com/mutual-fund"},
{"Initial_Urls": "https://www.livemint.com/insurance/news"},
{"Initial_Urls": "https://www.livemint.com/news/india"},
{"Initial_Urls": "https://www.livemint.com/market/mark-to-market"},
{"Initial_Urls": "https://www.livemint.com/videos"},
{"Initial_Urls": "https://www.livemint.com/education/news"},
{"Initial_Urls": "https://www.livemint.com/sports/olympics-news"},
{"Initial_Urls": "https://www.livemint.com/education"},
{"Initial_Urls": "https://www.livemint.com/sports/news"},
{"Initial_Urls": "https://www.livemint.com/sports/athletics-news"},
{"Initial_Urls": "https://www.livemint.com/mutual-fund/mint-30"},
{"Initial_Urls": "https://www.livemint.com/science/news"},
{"Initial_Urls": "https://www.livemint.com/photos"},
{"Initial_Urls": "https://www.livemint.com/news/world"},
{"Initial_Urls": "https://www.livemint.com/sports/football-news"},
{"Initial_Urls": "https://www.jagran.com/automobile"},
{"Initial_Urls": "https://www.livemint.com/sports"},
{"Initial_Urls": "https://www.livemint.com/sports/cricket-news"},
{"Initial_Urls": "https://www.livemint.com/sports/tennis-news"},
{"Initial_Urls": "https://www.livemint.com/opinion/columns"},
{"Initial_Urls": "https://www.livemint.com/opinion/drawbridge"},
{"Initial_Urls": "https://www.livemint.com/opinion/online-views"},
{"Initial_Urls": "https://www.livemint.com/science/health"},
{"Initial_Urls": "https://www.livemint.com/opinion/quick-edit"},
{"Initial_Urls": "https://www.livemint.com/politics/news"},
{"Initial_Urls": "https://www.livemint.com/science"},
{"Initial_Urls": "https://www.livemint.com/opinion"},
{"Initial_Urls": "https://www.livemint.com/ai"},
{"Initial_Urls": "https://www.livemint.com/auto-news"},
{"Initial_Urls": "https://www.livemint.com/ai/artificial-intelligence"},
{"Initial_Urls": "https://www.livemint.com/technology"},
{"Initial_Urls": "https://www.livemint.com/industry/media"},
{"Initial_Urls": "https://www.livemint.com/industry/advertising"},
{"Initial_Urls": "https://www.livemint.com/opinion/blogs"},
{"Initial_Urls": "https://www.livemint.com/industry/energy"},
{"Initial_Urls": "https://www.livemint.com/industry/agriculture"},
{"Initial_Urls": "https://www.livemint.com/industry/infrastructure"},
{"Initial_Urls": "https://www.livemint.com/technology/tech-reviews"},
{"Initial_Urls": "https://www.livemint.com/industry/telecom"},
{"Initial_Urls": "https://www.livemint.com/industry/infotech"},
{"Initial_Urls": "https://www.livemint.com/technology/apps"},
{"Initial_Urls": "https://www.livemint.com/industry/retail"},
{"Initial_Urls": "https://www.livemint.com/industry/human-resource"},
{"Initial_Urls": "https://www.livemint.com/technology/tech-news"},
{"Initial_Urls": "https://www.livemint.com/politics"},
{"Initial_Urls": "https://www.livemint.com/money/personal-finance"},
{"Initial_Urls": "https://www.livemint.com/money/ask-mint-money"},
{"Initial_Urls": "https://www.livemint.com/money/calculators"},
{"Initial_Urls": "https://www.livemint.com/companies/start-ups"},
{"Initial_Urls": "https://www.livemint.com/companies/news"},
{"Initial_Urls": "https://www.livemint.com/industry/banking"},
{"Initial_Urls": "https://www.indiatvnews.com/video/haqikat-kya-hai"},
{"Initial_Urls": "https://www.indiatvnews.com/cricket/live-scores"},
{"Initial_Urls": "https://www.livemint.com/industry"},
{"Initial_Urls": "https://www.livemint.com/technology/gadgets"},
{"Initial_Urls": "https://www.indiatvnews.com/lifestyle/fashion"},
{"Initial_Urls": "https://www.livemint.com/companies/people"},
{"Initial_Urls": "https://www.indiatvnews.com/lifestyle/beauty"},
{"Initial_Urls": "https://www.indiatvnews.com/lifestyle/relationships"},
{"Initial_Urls": "https://www.livemint.com/companies/company-results"},
{"Initial_Urls": "https://www.livemint.com/companies"},
{"Initial_Urls": "https://www.indiatvnews.com/salaamindia/"},
{"Initial_Urls": "https://www.livemint.com/industry/manufacturing"},
{"Initial_Urls": "https://www.indiatvnews.com/cms/inthepress"},
{"Initial_Urls": "https://www.indiatvnews.com/lifestyle/food"},
{"Initial_Urls": "https://www.indiatvnews.com/cms/advertise"},
{"Initial_Urls": "https://www.indiatvnews.com/cms/complaint-redressal"},
{"Initial_Urls": "https://www.livemint.com/money"},
{"Initial_Urls": "https://www.indiatvnews.com/lifestyle/travel"},
{"Initial_Urls": "https://www.indiatvnews.com/photos/sports"},
{"Initial_Urls": "https://www.indiatvnews.com/photos/fashion-lifestyle"},
{"Initial_Urls": "https://www.indiatvnews.com/entertainment/web-series"},
{"Initial_Urls": "https://www.indiatvnews.com/entertainment/bhojpuri"},
{"Initial_Urls": "https://www.indiatvnews.com/entertainment/regional-cinema"},
{"Initial_Urls": "https://www.indiatvnews.com/photos/politics"},
{"Initial_Urls": "https://www.indiatvnews.com/video/sports"},
{"Initial_Urls": "https://www.indiatvnews.com/photos/entertainment"},
{"Initial_Urls": "https://www.indiatvnews.com/video/astrology"},
{"Initial_Urls": "https://www.indiatvnews.com/video/entertainment"},
{"Initial_Urls": "https://www.indiatvnews.com/video/oh-my-god"},
{"Initial_Urls": "https://www.indiatvnews.com/video/aaj-ki-baat"},
{"Initial_Urls": "https://www.indiatvnews.com/video/elections"},
{"Initial_Urls": "https://www.indiatvnews.com/sports/other"},
{"Initial_Urls": "https://www.indiatvnews.com/video/aap-ki-adalat"},
{"Initial_Urls": "https://www.indiatvnews.com/sports/formula-1"},
{"Initial_Urls": "https://www.indiatvnews.com/sports/cricket"},
{"Initial_Urls": "https://www.indiatvnews.com/entertainment/movie-review"},
{"Initial_Urls": "https://www.indiatvnews.com/video/kurukshetra"},
{"Initial_Urls": "https://www.indiatvnews.com/entertainment/hollywood"},
{"Initial_Urls": "https://www.indiatvnews.com/entertainment/celebrities"},
{"Initial_Urls": "https://www.indiatvnews.com/entertainment/tv"},
{"Initial_Urls": "https://www.indiatvnews.com/technology/gadgets"},
{"Initial_Urls": "https://www.indiatvnews.com/entertainment/bollywood"},
{"Initial_Urls": "https://www.indiatvnews.com/crime"},
{"Initial_Urls": "https://www.indiatvnews.com/sports/tennis"},
{"Initial_Urls": "https://www.indiatvnews.com/auto"},
{"Initial_Urls": "https://www.indiatvnews.com/video/news"},
{"Initial_Urls": "https://www.indiatvnews.com/science"},
{"Initial_Urls": "https://www.indiatvnews.com/entertainment/masala"},
{"Initial_Urls": "https://digitalterminal.in/e-commerce"},
{"Initial_Urls": "https://www.indiatvnews.com/world"},
{"Initial_Urls": "https://digitalterminal.in/device"},
{"Initial_Urls": "https://digitalterminal.in/product-reviews"},
{"Initial_Urls": "https://digitalterminal.in/channel"},
{"Initial_Urls": "https://digitalterminal.in/interview"},
{"Initial_Urls": "https://digitalterminal.in/meet-your-boss"},
{"Initial_Urls": "https://digitalterminal.in/company-profile"},
{"Initial_Urls": "https://digitalterminal.in/telecom"},
{"Initial_Urls": "https://digitalterminal.in/regional"},
{"Initial_Urls": "https://digitalterminal.in/products"},
{"Initial_Urls": "https://digitalterminal.in/association-news"},
{"Initial_Urls": "https://digitalterminal.in/enterprise"},
{"Initial_Urls": "https://digitalterminal.in/trending"},
{"Initial_Urls": "https://digitalterminal.in/news"},
{"Initial_Urls": "https://www.indiatvnews.com/photos"},
{"Initial_Urls": "https://www.indiatvnews.com/education"},
{"Initial_Urls": "https://www.indiatvnews.com/sports"},
{"Initial_Urls": "https://www.indiatvnews.com/elections"},
{"Initial_Urls": "https://www.indiatvnews.com/entertainment"},
{"Initial_Urls": "https://www.indiatvnews.com/india"},
{"Initial_Urls": "https://www.indiatvnews.com/"},
{"Initial_Urls": "https://www.indiatvnews.com/video"},
{"Initial_Urls": "https://www.indiatvnews.com/education/results"},
{"Initial_Urls": "https://www.indiatvnews.com/trending"},
{"Initial_Urls": "https://www.indiatvnews.com/jobs"},
{"Initial_Urls": "https://www.indiatvnews.com/business"},
{"Initial_Urls": "https://www.indiatvnews.com/technology"},
{"Initial_Urls": "https://www.indiatvnews.com/lifestyle"}
]